CloneXls/ChangeLog.py
CloneXls/ChangeLogPandas.py
CloneXls/__init__.py
xlsclone-0.0.7.dist-info/LICENSE
xlsclone-0.0.7.dist-info/METADATA
xlsclone-0.0.7.dist-info/WHEEL
xlsclone-0.0.7.dist-info/top_level.txt
xlsclone-0.0.7.dist-info/RECORD
