Metadata-Version: 2.1
Name: xlsclone
Version: 0.0.7
Summary: Make a copy of an XLSX and keept it in sync with source, even if copied version is changed
Home-page: https://baangt.org
Author: Bernhard Buhl
Author-email: info@baangt.org
License: UNKNOWN
Platform: UNKNOWN
Classifier: Programming Language :: Python :: 3
Classifier: License :: OSI Approved :: MIT License
Classifier: Operating System :: OS Independent
Requires-Python: >=3.6
Requires-Dist: openpyxl
